CHANGELOG
LICENSE
MANIFEST.in
README.rst
pystress.py
setup.py
pystress.egg-info/PKG-INFO
pystress.egg-info/SOURCES.txt
pystress.egg-info/dependency_links.txt
pystress.egg-info/entry_points.txt
pystress.egg-info/namespace_packages.txt
pystress.egg-info/not-zip-safe
pystress.egg-info/top_level.txt