Metadata-Version: 1.1
Name: pystress
Version: 0.2.0
Summary: Simple CPU stresser in Python
Home-page: https://github.com/shichao-an/pystress
Author: Shichao An
Author-email: shichao.an@nyu.edu
License: BSD
Keywords: pystress
Platform: UNKNOWN
Classifier: Environment :: Console
Classifier: License :: OSI Approved :: BSD License
Classifier: Programming Language :: Python
Classifier: Programming Language :: Python :: 2
